poetry_monoranger_plugin/__init__.py
poetry_monoranger_plugin/config.py
poetry_monoranger_plugin/export_modifier.py
poetry_monoranger_plugin/lock_modifier.py
poetry_monoranger_plugin/monorepo_adder.py
poetry_monoranger_plugin/path_dep_pinner.py
poetry_monoranger_plugin/plugin.py
poetry_monoranger_plugin/venv_modifier.py
poetry_monoranger_plugin-0.4.1.dist-info/LICENSE
poetry_monoranger_plugin-0.4.1.dist-info/METADATA
poetry_monoranger_plugin-0.4.1.dist-info/WHEEL
poetry_monoranger_plugin-0.4.1.dist-info/entry_points.txt
poetry_monoranger_plugin-0.4.1.dist-info/RECORD
