Metadata-Version: 2.3
Name: poetry-monoranger-plugin
Version: 0.4.1
Summary: Monoranger is a plugin for Poetry that helps you manage your monorepo, enabling shared lockfiles and virtual environments.
License: Apache-2.0
Keywords: packaging,poetry,monorepo,lockfile,virtualenv
Author: Andreas Georgiou
Author-email: andreas.x.georgiou@gsk.com
Requires-Python: >=3.9,<4.0
Classifier: License :: OSI Approved :: Apache Software License
Classifier: Programming Language :: Python :: 3
Classifier: Programming Language :: Python :: 3.9
Classifier: Programming Language :: Python :: 3.10
Classifier: Programming Language :: Python :: 3.11
Classifier: Programming Language :: Python :: 3.12
Classifier: Programming Language :: Python :: 3.13
Classifier: Topic :: Software Development :: Build Tools
Classifier: Topic :: Software Development :: Libraries :: Python Modules
Requires-Dist: poetry (>=1.8.0)
Project-URL: Repository, https://github.com/ag14774/poetry-monoranger-plugin
